gcp_auth_helper/__init__.py
gcp_auth_helper/constants.py
gcp_auth_helper/credentials.py
gcp_auth_helper-0.1.1.dist-info/METADATA
gcp_auth_helper-0.1.1.dist-info/WHEEL
gcp_auth_helper-0.1.1.dist-info/top_level.txt
gcp_auth_helper-0.1.1.dist-info/RECORD
