Metadata-Version: 2.4
Name: gcp-auth-helper
Version: 0.1.1
Summary: Simple GCP credentials helper for local and production environments.
Home-page: https://github.com/lucasfonsecads/gcp-auth-helper.git
Author: Lucas Fonseca
Classifier: Programming Language :: Python :: 3
Classifier: License :: OSI Approved :: MIT License
Classifier: Operating System :: OS Independent
Requires-Python: >=3.8
Requires-Dist: google-auth
Requires-Dist: google-auth-oauthlib
Requires-Dist: google-auth-httplib2
